toil_pindel/VERSION
toil_pindel/__init__.py
toil_pindel/__main__.py
toil_pindel/cli.py
toil_pindel/commands.py
toil_pindel/exceptions.py
toil_pindel/utils.py
toil_pindel/validators.py
toil_pindel/data/README.md
toil_pindel-1.1.8.dist-info/LICENSE
toil_pindel-1.1.8.dist-info/METADATA
toil_pindel-1.1.8.dist-info/WHEEL
toil_pindel-1.1.8.dist-info/entry_points.txt
toil_pindel-1.1.8.dist-info/top_level.txt
toil_pindel-1.1.8.dist-info/RECORD
